APC_Temp_fetch/__init__.py
APC_Temp_fetch/base.py
APC_Temp_fetch/cli.py
APC_Temp_fetch/cs121.py
APC_Temp_fetch/cs141.py
APC_Temp_fetch/frmnc.py
APC_Temp_fetch/frmnc666.py
APC_Temp_fetch/gden_nt07.py
APC_Temp_fetch/old.py
APC_Temp_fetch/py.typed
apc_temp_fetch-0.0.9.dist-info/entry_points.txt
apc_temp_fetch-0.0.9.dist-info/LICENSE
apc_temp_fetch-0.0.9.dist-info/WHEEL
apc_temp_fetch-0.0.9.dist-info/METADATA
apc_temp_fetch-0.0.9.dist-info/RECORD
