Metadata-Version: 2.1
Name: APC-Temp-fetch
Version: 0.0.9
Summary: APC/Schneider UPS current temperature fetchers
Author-email: Alain Zscheile <fogti+atf@ytrizja.de>
Requires-Python: >=3.9
Classifier: Development Status :: 4 - Beta
Classifier: License :: OSI Approved :: Apache Software License
Requires-Dist: requests >=2.0
Requires-Dist: pytest >=7.1.2 ; extra == "test"
Project-URL: Home, https://github.com/YZITE/APC_Temp_fetch
Provides-Extra: test
